pdf2epub/__init__.py
pdf2epub/cli.py
pdf2epub/mark2epub.py
pdf2epub/pdf2md.py
pdf2epub/postprocessing/__init__.py
pdf2epub/postprocessing/postprocessor.py
pdf2epub/postprocessing/prompt.txt
pdf2epub/postprocessing/ai/__init__.py
pdf2epub/postprocessing/ai/anthropicapi.py
pdf2epub-0.1.2.dist-info/licenses/AUTHORS.md
pdf2epub-0.1.2.dist-info/licenses/LICENSE
pdf2epub-0.1.2.dist-info/METADATA
pdf2epub-0.1.2.dist-info/WHEEL
pdf2epub-0.1.2.dist-info/entry_points.txt
pdf2epub-0.1.2.dist-info/top_level.txt
pdf2epub-0.1.2.dist-info/RECORD
