Metadata-Version: 2.4
Name: pdf2epub
Version: 0.1.2
Summary: Convert PDF files to EPUB format via Markdown with intelligent layout detection
Author: porfanid
Maintainer: porfanid
License: MIT
Project-URL: Homepage, https://github.com/porfanid/pdf2epub
Project-URL: Repository, https://github.com/porfanid/pdf2epub
Project-URL: Issues, https://github.com/porfanid/pdf2epub/issues
Project-URL: Documentation, https://github.com/porfanid/pdf2epub/blob/main/docs/README.md
Project-URL: Changelog, https://github.com/porfanid/pdf2epub/blob/main/CHANGELOG.md
Project-URL: Discussions, https://github.com/porfanid/pdf2epub/discussions
Keywords: pdf,epub,markdown,conversion,ebook,ai,postprocessing
Classifier: Development Status :: 4 - Beta
Classifier: Intended Audience :: Developers
Classifier: Intended Audience :: End Users/Desktop
Classifier: Operating System :: OS Independent
Classifier: Programming Language :: Python :: 3
Classifier: Programming Language :: Python :: 3.10
Classifier: Programming Language :: Python :: 3.11
Classifier: Programming Language :: Python :: 3.12
Classifier: Topic :: Multimedia :: Graphics :: Graphics Conversion
Classifier: Topic :: Text Processing :: Markup
Classifier: Topic :: Utilities
Requires-Python: >=3.10
License-File: LICENSE
License-File: AUTHORS.md
Requires-Dist: markdown
Requires-Dist: marker-pdf==0.3.10
Requires-Dist: transformers==4.45.2
Requires-Dist: anthropic==0.39.0
Requires-Dist: torch
Requires-Dist: pillow
Requires-Dist: regex
Provides-Extra: full
Requires-Dist: marker-pdf==0.3.10; extra == "full"
Requires-Dist: transformers==4.45.2; extra == "full"
Requires-Dist: anthropic==0.39.0; extra == "full"
Requires-Dist: torch; extra == "full"
Requires-Dist: pillow; extra == "full"
Requires-Dist: regex; extra == "full"
Provides-Extra: dev
Requires-Dist: pytest>=7.0; extra == "dev"
Requires-Dist: pytest-cov>=4.0; extra == "dev"
Requires-Dist: black>=23.0; extra == "dev"
Requires-Dist: flake8>=6.0; extra == "dev"
Requires-Dist: mypy>=1.0; extra == "dev"
Dynamic: license-file
